[{"Runs":"8","Balls":"4","Sixes":"0","SR":"200.00","Fours":"1","BatsmanName":"JP Duminy"},{"Runs":"23","Balls":"28","Sixes":"0","SR":"82.14","Fours":"1","BatsmanName":"JP Duminy"},{"Runs":"12","Balls":"13","Sixes":"0","SR":"92.30","Fours":"2","BatsmanName":"JP Duminy"},{"Runs":"6","Balls":"15","Sixes":"0","SR":"40.00","Fours":"0","BatsmanName":"JP Duminy"},{"Runs":"115","Balls":"100","Sixes":"3","SR":"115.00","Fours":"9","BatsmanName":"JP Duminy"},{"Runs":"115","Balls":"100","Sixes":"3","SR":"115.00","Fours":"9","BatsmanName":"JP Duminy"},{"Runs":"8","Balls":"4","Sixes":"0","SR":"200.00","Fours":"1","BatsmanName":"JP Duminy"},{"Runs":"12","Balls":"13","Sixes":"0","SR":"92.30","Fours":"2","BatsmanName":"JP Duminy"},{"Runs":"23","Balls":"28","Sixes":"0","SR":"82.14","Fours":"1","BatsmanName":"JP Duminy"},{"Runs":"6","Balls":"15","Sixes":"0","SR":"40.00","Fours":"0","BatsmanName":"JP Duminy"},{"Runs":"8","Balls":"4","Sixes":"0","SR":"200.00","Fours":"1","BatsmanName":"JP Duminy"},{"Runs":"23","Balls":"28","Sixes":"0","SR":"82.14","Fours":"1","BatsmanName":"JP Duminy"},{"Runs":"12","Balls":"13","Sixes":"0","SR":"92.30","Fours":"2","BatsmanName":"JP Duminy"},{"Runs":"6","Balls":"15","Sixes":"0","SR":"40.00","Fours":"0","BatsmanName":"JP Duminy"},{"Runs":"115","Balls":"100","Sixes":"3","SR":"115.00","Fours":"9","BatsmanName":"JP Duminy"},{"Runs":"115","Balls":"100","Sixes":"3","SR":"115.00","Fours":"9","BatsmanName":"JP Duminy"},{"Runs":"23","Balls":"28","Sixes":"0","SR":"82.14","Fours":"1","BatsmanName":"JP Duminy"},{"Runs":"6","Balls":"15","Sixes":"0","SR":"40.00","Fours":"0","BatsmanName":"JP Duminy"},{"Runs":"12","Balls":"13","Sixes":"0","SR":"92.30","Fours":"2","BatsmanName":"JP Duminy"},{"Runs":"8","Balls":"4","Sixes":"0","SR":"200.00","Fours":"1","BatsmanName":"JP Duminy"}]