[{"Overs":"9.2","Maiden":"1","Runs":"65","Wicket":"2","ECON":"6.96","WD":"27","NB":"9"},{"Overs":"9.2","Maiden":"1","Runs":"65","Wicket":"2","ECON":"6.96","WD":"27","NB":"9"},{"Overs":"9.2","Maiden":"1","Runs":"65","Wicket":"2","ECON":"6.96","WD":"27","NB":"9"},{"Overs":"9.2","Maiden":"1","Runs":"65","Wicket":"2","ECON":"6.96","WD":"27","NB":"9"},{"Overs":"9.2","Maiden":"1","Runs":"65","Wicket":"2","ECON":"6.96","WD":"27","NB":"9"},{"Overs":"9.2","Maiden":"1","Runs":"65","Wicket":"2","ECON":"6.96","WD":"27","NB":"9"}]