[{"Overs":"9.4","Maiden":"0","Runs":"74","Wicket":"0","ECON":"7.65","WD":"28","NB":"8"},{"Overs":"9.4","Maiden":"0","Runs":"74","Wicket":"0","ECON":"7.65","WD":"28","NB":"8"},{"Overs":"9.4","Maiden":"0","Runs":"74","Wicket":"0","ECON":"7.65","WD":"28","NB":"8"},{"Overs":"9.4","Maiden":"0","Runs":"74","Wicket":"0","ECON":"7.65","WD":"28","NB":"8"},{"Overs":"9.4","Maiden":"0","Runs":"74","Wicket":"0","ECON":"7.65","WD":"28","NB":"8"},{"Overs":"9.4","Maiden":"0","Runs":"74","Wicket":"0","ECON":"7.65","WD":"28","NB":"8"}]