[{"Runs":"13","Balls":"19","Sixes":"0","SR":"68.42","Fours":"1","BatsmanName":"JF Mooney"},{"Runs":"12","Balls":"16","Sixes":"0","SR":"75.00","Fours":"1","BatsmanName":"JF Mooney"},{"Runs":"8","Balls":"15","Sixes":"0","SR":"53.33","Fours":"0","BatsmanName":"JF Mooney"},{"Runs":"10","Balls":"4","Sixes":"0","SR":"250.00","Fours":"2","BatsmanName":"JF Mooney"},{"Runs":"6","Balls":"5","Sixes":"0","SR":"120.00","Fours":"1","BatsmanName":"JF Mooney"},{"Runs":"2","Balls":"6","Sixes":"0","SR":"33.33","Fours":"0","BatsmanName":"JF Mooney"},{"Runs":"12","Balls":"16","Sixes":"0","SR":"75.00","Fours":"1","BatsmanName":"JF Mooney"},{"Runs":"10","Balls":"4","Sixes":"0","SR":"250.00","Fours":"2","BatsmanName":"JF Mooney"},{"Runs":"6","Balls":"5","Sixes":"0","SR":"120.00","Fours":"1","BatsmanName":"JF Mooney"},{"Runs":"8","Balls":"15","Sixes":"0","SR":"53.33","Fours":"0","BatsmanName":"JF Mooney"},{"Runs":"13","Balls":"19","Sixes":"0","SR":"68.42","Fours":"1","BatsmanName":"JF Mooney"},{"Runs":"2","Balls":"6","Sixes":"0","SR":"33.33","Fours":"0","BatsmanName":"JF Mooney"},{"Runs":"10","Balls":"4","Sixes":"0","SR":"250.00","Fours":"2","BatsmanName":"JF Mooney"},{"Runs":"6","Balls":"5","Sixes":"0","SR":"120.00","Fours":"1","BatsmanName":"JF Mooney"},{"Runs":"12","Balls":"16","Sixes":"0","SR":"75.00","Fours":"1","BatsmanName":"JF Mooney"},{"Runs":"13","Balls":"19","Sixes":"0","SR":"68.42","Fours":"1","BatsmanName":"JF Mooney"},{"Runs":"8","Balls":"15","Sixes":"0","SR":"53.33","Fours":"0","BatsmanName":"JF Mooney"},{"Runs":"2","Balls":"6","Sixes":"0","SR":"33.33","Fours":"0","BatsmanName":"JF Mooney"},{"Runs":"13","Balls":"19","Sixes":"0","SR":"68.42","Fours":"1","BatsmanName":"JF Mooney"},{"Runs":"8","Balls":"15","Sixes":"0","SR":"53.33","Fours":"0","BatsmanName":"JF Mooney"},{"Runs":"6","Balls":"5","Sixes":"0","SR":"120.00","Fours":"1","BatsmanName":"JF Mooney"},{"Runs":"2","Balls":"6","Sixes":"0","SR":"33.33","Fours":"0","BatsmanName":"JF Mooney"},{"Runs":"10","Balls":"4","Sixes":"0","SR":"250.00","Fours":"2","BatsmanName":"JF Mooney"},{"Runs":"12","Balls":"16","Sixes":"0","SR":"75.00","Fours":"1","BatsmanName":"JF Mooney"}]