[{"Overs":"10","Maiden":"0","Runs":"48","Wicket":"2","ECON":"4.80","WD":"35","NB":"6"},{"Overs":"10","Maiden":"0","Runs":"48","Wicket":"2","ECON":"4.80","WD":"35","NB":"6"},{"Overs":"10","Maiden":"0","Runs":"48","Wicket":"2","ECON":"4.80","WD":"35","NB":"6"},{"Overs":"10","Maiden":"0","Runs":"48","Wicket":"2","ECON":"4.80","WD":"35","NB":"6"},{"Overs":"10","Maiden":"0","Runs":"48","Wicket":"2","ECON":"4.80","WD":"35","NB":"6"},{"Overs":"10","Maiden":"0","Runs":"48","Wicket":"2","ECON":"4.80","WD":"35","NB":"6"}]