[{"Overs":"9","Maiden":"0","Runs":"33","Wicket":"5","ECON":"3.66","WD":"33","NB":"2"},{"Overs":"9","Maiden":"0","Runs":"33","Wicket":"5","ECON":"3.66","WD":"33","NB":"2"},{"Overs":"9","Maiden":"0","Runs":"33","Wicket":"5","ECON":"3.66","WD":"33","NB":"2"},{"Overs":"9","Maiden":"0","Runs":"33","Wicket":"5","ECON":"3.66","WD":"33","NB":"2"},{"Overs":"9","Maiden":"0","Runs":"33","Wicket":"5","ECON":"3.66","WD":"33","NB":"2"},{"Overs":"9","Maiden":"0","Runs":"33","Wicket":"5","ECON":"3.66","WD":"33","NB":"2"}]