[{"Overs":"8","Maiden":"0","Runs":"60","Wicket":"0","ECON":"7.50","WD":"25","NB":"8"},{"Overs":"8","Maiden":"0","Runs":"60","Wicket":"0","ECON":"7.50","WD":"25","NB":"8"},{"Overs":"8","Maiden":"0","Runs":"60","Wicket":"0","ECON":"7.50","WD":"25","NB":"8"},{"Overs":"8","Maiden":"0","Runs":"60","Wicket":"0","ECON":"7.50","WD":"25","NB":"8"},{"Overs":"8","Maiden":"0","Runs":"60","Wicket":"0","ECON":"7.50","WD":"25","NB":"8"},{"Overs":"8","Maiden":"0","Runs":"60","Wicket":"0","ECON":"7.50","WD":"25","NB":"8"}]